ftpshutil/__init__.py
ftpshutil/dircrc.py
ftpshutil/ftpconfig.py
ftpshutil/ftpshutil.py
ftpshutil/tests/__init__.py
ftpshutil/tests/test_all.py
ftpshutil-0.0.1.dist-info/LICENSE
ftpshutil-0.0.1.dist-info/METADATA
ftpshutil-0.0.1.dist-info/WHEEL
ftpshutil-0.0.1.dist-info/top_level.txt
ftpshutil-0.0.1.dist-info/RECORD
