Metadata-Version: 2.1
Name: ftpshutil
Version: 0.0.1
Summary: Ftplib Shutil like functionality
Home-page: https://github.com/rumca-js/ftplibshutil
Author: Piotr Zielinski
Author-email: rozbujnik@gmail.com
License: UNKNOWN
Platform: UNKNOWN
Classifier: Programming Language :: Python :: 3
Classifier: License :: OSI Approved :: MIT License
Classifier: Operating System :: OS Independent
Requires-Python: >=3.6
